aspose/svg/__init__.pyi
aspose/svg/builder/__init__.pyi
aspose/svg/collections/__init__.pyi
aspose/svg/converters/__init__.pyi
aspose/svg/datatypes/__init__.pyi
aspose/svg/diagnostics/__init__.pyi
aspose/svg/dom/__init__.pyi
aspose/svg/dom/attributes/__init__.pyi
aspose/svg/dom/css/__init__.pyi
aspose/svg/dom/events/__init__.pyi
aspose/svg/dom/mutations/__init__.pyi
aspose/svg/dom/traversal/__init__.pyi
aspose/svg/dom/traversal/filters/__init__.pyi
aspose/svg/dom/views/__init__.pyi
aspose/svg/dom/xpath/__init__.pyi
aspose/svg/drawing/__init__.pyi
aspose/svg/events/__init__.pyi
aspose/svg/filters/__init__.pyi
aspose/svg/imagevectorization/__init__.pyi
aspose/svg/io/__init__.pyi
aspose/svg/net/__init__.pyi
aspose/svg/net/headers/__init__.pyi
aspose/svg/net/messagefilters/__init__.pyi
aspose/svg/net/messagehandlers/__init__.pyi
aspose/svg/paths/__init__.pyi
aspose/svg/rendering/__init__.pyi
aspose/svg/rendering/fonts/__init__.pyi
aspose/svg/rendering/image/__init__.pyi
aspose/svg/rendering/pdf/__init__.pyi
aspose/svg/rendering/pdf/encryption/__init__.pyi
aspose/svg/rendering/skia/__init__.pyi
aspose/svg/rendering/xps/__init__.pyi
aspose/svg/saving/__init__.pyi
aspose/svg/saving/resourcehandlers/__init__.pyi
aspose/svg/services/__init__.pyi
aspose/svg/toolkit/__init__.pyi
aspose/svg/toolkit/optimizers/__init__.pyi
aspose/svg/window/__init__.pyi
aspose/__init__.py
aspose/pycore.cpython-310-darwin.so
aspose/pycore.cpython-311-darwin.so
aspose/pycore.cpython-312-darwin.so
aspose/pycore.cpython-313-darwin.so
aspose/pycore.cpython-35m-darwin.so
aspose/pycore.cpython-36m-darwin.so
aspose/pycore.cpython-37m-darwin.so
aspose/pycore.cpython-38-darwin.so
aspose/pycore.cpython-39-darwin.so
aspose/pydrawing.cpython-310-darwin.so
aspose/pydrawing.cpython-311-darwin.so
aspose/pydrawing.cpython-312-darwin.so
aspose/pydrawing.cpython-313-darwin.so
aspose/pydrawing.cpython-35m-darwin.so
aspose/pydrawing.cpython-36m-darwin.so
aspose/pydrawing.cpython-37m-darwin.so
aspose_svg_net-25.12.0.dist-info/METADATA
aspose_svg_net-25.12.0.dist-info/WHEEL
aspose_svg_net-25.12.0.dist-info/entry_points.txt
aspose_svg_net-25.12.0.dist-info/top_level.txt
aspose_svg_net-25.12.0.dist-info/RECORD
